djform_navigation-1.1.data/data/1/change_form.html
djform_navigation-1.1.data/data/2/module.js
form_navigation/__init__.py
form_navigation/apps.py
form_navigation/migrations/__init__.py
form_navigation/static/form_navigation/change_form_prev_next.js
form_navigation/static/form_navigation/module.js
form_navigation/templates/admin/change_form.html
djform_navigation-1.1.dist-info/LICENSE.txt
djform_navigation-1.1.dist-info/METADATA
djform_navigation-1.1.dist-info/WHEEL
djform_navigation-1.1.dist-info/top_level.txt
djform_navigation-1.1.dist-info/RECORD
